{
  "objects": [
    {
      "size": "large",
      "rotation": 194.38258778685605,
      "3d_coords": [
        -1.0127110481262207,
        2.007277250289917,
        0.30000001192092896
      ],
      "shape": "cube",
      "material": "rubber",
      "color": "green",
      "pixel_coords": [
        367,
        174,
        13.146352767944336
      ]
    },
    {
      "size": "small",
      "rotation": 210.26199335459722,
      "3d_coords": [
        -2.259434461593628,
        -1.0653948783874512,
        0.30000001192092896
      ],
      "shape": "cylinder",
      "material": "rubber",
      "color": "purple",
      "pixel_coords": [
        190,
        197,
        12.24921703338623
      ]
    },
    {
      "size": "large",
      "rotation": 239.4697218079788,
      "3d_coords": [
        2.53255558013916,
        2.9139299392700195,
        0.30000001192092896
      ],
      "shape": "cube",
      "material": "rubber",
      "color": "purple",
      "pixel_coords": [
        560,
        226,
        11.266499519348145
      ]
    },
    {
      "size": "small",
      "rotation": 140.79513350082752,
      "3d_coords": [
        2.9525227546691895,
        -0.7724276781082153,
        0.30000001192092896
      ],
      "shape": "cube",
      "material": "rubber",
      "color": "blue",
      "pixel_coords": [
        423,
        322,
        8.897196769714355
      ]
    },
    {
      "size": "small",
      "rotation": 201.37277051309658,
      "3d_coords": [
        0.07631485909223557,
        -2.105520248413086,
        0.30000001192092896
      ],
      "shape": "sphere",
      "material": "rubber",
      "color": "purple",
      "pixel_coords": [
        211,
        268,
        10.084179878234863
      ]
    },
    {
      "size": "small",
      "rotation": 216.11532524842733,
      "3d_coords": [
        1.0016052722930908,
        1.554975986480713,
        0.30000001192092896
      ],
      "shape": "sphere",
      "material": "rubber",
      "color": "gray",
      "pixel_coords": [
        431,
        217,
        11.53087329864502
      ]
    },
    {
      "size": "large",
      "rotation": 132.22083524010748,
      "3d_coords": [
        2.442150592803955,
        -2.593971014022827,
        0.30000001192092896
      ],
      "shape": "sphere",
      "material": "rubber",
      "color": "blue",
      "pixel_coords": [
        284,
        360,
        8.210988998413086
      ]
    },
    {
      "size": "small",
      "rotation": 83.46189741457606,
      "3d_coords": [
        2.534332036972046,
        -1.7517794370651245,
        0.30000001192092896
      ],
      "shape": "cylinder",
      "material": "rubber",
      "color": "purple",
      "pixel_coords": [
        343,
        336,
        8.625307083129883
      ]
    },
    {
      "size": "small",
      "rotation": 11.321804298095671,
      "3d_coords": [
        -0.8701743483543396,
        -2.887930393218994,
        0.30000001192092896
      ],
      "shape": "sphere",
      "material": "rubber",
      "color": "green",
      "pixel_coords": [
        131,
        260,
        10.280298233032227
      ]
    },
    {
      "size": "large",
      "rotation": 185.3719655121151,
      "3d_coords": [
        -0.4331129491329193,
        -1.2433576583862305,
        0.30000001192092896
      ],
      "shape": "cylinder",
      "material": "rubber",
      "color": "yellow",
      "pixel_coords": [
        241,
        237,
        10.915852546691895
      ]
    },
    {
      "size": "large",
      "rotation": 137.4407271039711,
      "3d_coords": [
        2.844069480895996,
        0.403888463973999,
        0.30000001192092896
      ],
      "shape": "cube",
      "material": "rubber",
      "color": "purple",
      "pixel_coords": [
        475,
        287,
        9.635990142822266
      ]
    },
    {
      "size": "large",
      "rotation": 213.9124497067474,
      "3d_coords": [
        1.5300402641296387,
        2.4927289485931396,
        0.30000001192092896
      ],
      "shape": "cylinder",
      "material": "rubber",
      "color": "purple",
      "pixel_coords": [
        493,
        212,
        11.704815864562988
      ]
    },
    {
      "size": "large",
      "rotation": 14.187325121867765,
      "3d_coords": [
        2.9778473377227783,
        2.0045244693756104,
        0.30000001192092896
      ],
      "shape": "cylinder",
      "material": "rubber",
      "color": "brown",
      "pixel_coords": [
        551,
        254,
        10.451383590698242
      ]
    },
    {
      "size": "large",
      "rotation": 350.2884909807532,
      "3d_coords": [
        -2.5233442783355713,
        2.0329413414001465,
        0.30000001192092896
      ],
      "shape": "sphere",
      "material": "rubber",
      "color": "cyan",
      "pixel_coords": [
        317,
        151,
        14.18047046661377
      ]
    },
    {
      "size": "small",
      "rotation": 45.102682627579334,
      "3d_coords": [
        -1.016945481300354,
        0.033138275146484375,
        0.30000001192092896
      ],
      "shape": "cylinder",
      "material": "rubber",
      "color": "cyan",
      "pixel_coords": [
        283,
        203,
        12.032186508178711
      ]
    },
    {
      "size": "small",
      "rotation": 129.9177830942032,
      "3d_coords": [
        -2.417569637298584,
        2.8608059883117676,
        0.30000001192092896
      ],
      "shape": "cube",
      "material": "rubber",
      "color": "yellow",
      "pixel_coords": [
        351,
        143,
        14.577507972717285
      ]
    },
    {
      "size": "small",
      "rotation": 187.3246115617299,
      "3d_coords": [
        -1.7976511716842651,
        0.3614942133426666,
        0.30000001192092896
      ],
      "shape": "sphere",
      "material": "rubber",
      "color": "brown",
      "pixel_coords": [
        272,
        184,
        12.744913101196289
      ]
    },
    {
      "size": "large",
      "rotation": 81.62362258076773,
      "3d_coords": [
        -2.146376848220825,
        -2.896388053894043,
        0.30000001192092896
      ],
      "shape": "sphere",
      "material": "rubber",
      "color": "cyan",
      "pixel_coords": [
        94,
        230,
        11.136880874633789
      ]
    },
    {
      "size": "large",
      "rotation": 325.7231300260669,
      "3d_coords": [
        -2.9985768795013428,
        -1.5816709995269775,
        0.30000001192092896
      ],
      "shape": "sphere",
      "material": "rubber",
      "color": "brown",
      "pixel_coords": [
        144,
        191,
        12.455974578857422
      ]
    },
    {
      "size": "large",
      "rotation": 338.9537923008572,
      "3d_coords": [
        1.803519606590271,
        -1.3838773965835571,
        0.30000001192092896
      ],
      "shape": "cube",
      "material": "rubber",
      "color": "red",
      "pixel_coords": [
        327,
        301,
        9.326736450195312
      ]
    }
  ],
  "directions": {
    "front": [
      0.754490315914154,
      -0.6563112735748291,
      -0.0
    ],
    "behind": [
      -0.754490315914154,
      0.6563112735748291,
      0.0
    ],
    "left": [
      -0.6563112735748291,
      -0.7544902563095093,
      0.0
    ],
    "below": [
      -0.0,
      -0.0,
      -1.0
    ],
    "right": [
      0.6563112735748291,
      0.7544902563095093,
      -0.0
    ],
    "above": [
      0.0,
      0.0,
      1.0
    ]
  },
  "split": "new",
  "image_index": 2005,
  "image_filename": "CLEVR_new_002005.png",
  "relationships": {
    "front": [
      [
        1,
        2,
        3,
        4,
        5,
        6,
        7,
        8,
        9,
        10,
        11,
        12,
        14,
        16,
        17,
        18,
        19
      ],
      [
        2,
        3,
        4,
        5,
        6,
        7,
        8,
        9,
        10,
        11,
        12,
        14,
        17,
        19
      ],
      [
        3,
        4,
        6,
        7,
        8,
        9,
        10,
        12,
        17,
        19
      ],
      [
        6,
        7
      ],
      [
        3,
        6,
        7,
        10,
        19
      ],
      [
        2,
        3,
        4,
        6,
        7,
        8,
        9,
        10,
        12,
        17,
        19
      ],
      [],
      [
        6
      ],
      [
        3,
        4,
        6,
        7,
        10,
        19
      ],
      [
        3,
        4,
        6,
        7,
        8,
        10,
        12,
        19
      ],
      [
        3,
        6,
        7,
        19
      ],
      [
        2,
        3,
        4,
        5,
        6,
        7,
        8,
        9,
        10,
        12,
        17,
        19
      ],
      [
        3,
        4,
        6,
        7,
        8,
        10,
        19
      ],
      [
        0,
        1,
        2,
        3,
        4,
        5,
        6,
        7,
        8,
        9,
        10,
        11,
        12,
        14,
        16,
        17,
        18,
        19
      ],
      [
        2,
        3,
        4,
        5,
        6,
        7,
        8,
        9,
        10,
        11,
        12,
        17,
        19
      ],
      [
        0,
        1,
        2,
        3,
        4,
        5,
        6,
        7,
        8,
        9,
        10,
        11,
        12,
        13,
        14,
        16,
        17,
        18,
        19
      ],
      [
        1,
        2,
        3,
        4,
        5,
        6,
        7,
        8,
        9,
        10,
        11,
        12,
        14,
        17,
        18,
        19
      ],
      [
        3,
        4,
        6,
        7,
        8,
        9,
        10,
        12,
        19
      ],
      [
        1,
        2,
        3,
        4,
        5,
        6,
        7,
        8,
        9,
        10,
        11,
        12,
        14,
        17,
        19
      ],
      [
        3,
        6,
        7
      ]
    ],
    "behind": [
      [
        13,
        15
      ],
      [
        0,
        13,
        15,
        16,
        18
      ],
      [
        0,
        1,
        5,
        11,
        13,
        14,
        15,
        16,
        18
      ],
      [
        0,
        1,
        2,
        4,
        5,
        8,
        9,
        10,
        11,
        12,
        13,
        14,
        15,
        16,
        17,
        18,
        19
      ],
      [
        0,
        1,
        2,
        5,
        8,
        9,
        11,
        12,
        13,
        14,
        15,
        16,
        17,
        18
      ],
      [
        0,
        1,
        11,
        13,
        14,
        15,
        16,
        18
      ],
      [
        0,
        1,
        2,
        3,
        4,
        5,
        7,
        8,
        9,
        10,
        11,
        12,
        13,
        14,
        15,
        16,
        17,
        18,
        19
      ],
      [
        0,
        1,
        2,
        3,
        4,
        5,
        8,
        9,
        10,
        11,
        12,
        13,
        14,
        15,
        16,
        17,
        18,
        19
      ],
      [
        0,
        1,
        2,
        5,
        9,
        11,
        12,
        13,
        14,
        15,
        16,
        17,
        18
      ],
      [
        0,
        1,
        2,
        5,
        11,
        13,
        14,
        15,
        16,
        17,
        18
      ],
      [
        0,
        1,
        2,
        4,
        5,
        8,
        9,
        11,
        12,
        13,
        14,
        15,
        16,
        17,
        18
      ],
      [
        0,
        1,
        13,
        14,
        15,
        16,
        18
      ],
      [
        0,
        1,
        2,
        5,
        9,
        11,
        13,
        14,
        15,
        16,
        17,
        18
      ],
      [
        15
      ],
      [
        0,
        1,
        13,
        15,
        16,
        18
      ],
      [],
      [
        0,
        13,
        15
      ],
      [
        0,
        1,
        2,
        5,
        11,
        13,
        14,
        15,
        16,
        18
      ],
      [
        0,
        13,
        15,
        16
      ],
      [
        0,
        1,
        2,
        4,
        5,
        8,
        9,
        10,
        11,
        12,
        13,
        14,
        15,
        16,
        17,
        18
      ]
    ],
    "right": [
      [
        2,
        3,
        5,
        10,
        11,
        12
      ],
      [
        0,
        2,
        3,
        4,
        5,
        6,
        7,
        9,
        10,
        11,
        12,
        13,
        14,
        15,
        16,
        19
      ],
      [],
      [
        2,
        5,
        10,
        11,
        12
      ],
      [
        0,
        2,
        3,
        5,
        6,
        7,
        9,
        10,
        11,
        12,
        13,
        14,
        15,
        16,
        19
      ],
      [
        2,
        10,
        11,
        12
      ],
      [
        0,
        2,
        3,
        5,
        7,
        10,
        11,
        12,
        13,
        15,
        19
      ],
      [
        0,
        2,
        3,
        5,
        10,
        11,
        12,
        15
      ],
      [
        0,
        1,
        2,
        3,
        4,
        5,
        6,
        7,
        9,
        10,
        11,
        12,
        13,
        14,
        15,
        16,
        19
      ],
      [
        0,
        2,
        3,
        5,
        6,
        7,
        10,
        11,
        12,
        13,
        14,
        15,
        16,
        19
      ],
      [
        2,
        11,
        12
      ],
      [
        2,
        12
      ],
      [
        2
      ],
      [
        0,
        2,
        3,
        5,
        7,
        10,
        11,
        12,
        15,
        19
      ],
      [
        0,
        2,
        3,
        5,
        6,
        7,
        10,
        11,
        12,
        13,
        15,
        19
      ],
      [
        0,
        2,
        3,
        5,
        10,
        11,
        12
      ],
      [
        0,
        2,
        3,
        5,
        6,
        7,
        10,
        11,
        12,
        13,
        14,
        15,
        19
      ],
      [
        0,
        1,
        2,
        3,
        4,
        5,
        6,
        7,
        8,
        9,
        10,
        11,
        12,
        13,
        14,
        15,
        16,
        18,
        19
      ],
      [
        0,
        1,
        2,
        3,
        4,
        5,
        6,
        7,
        8,
        9,
        10,
        11,
        12,
        13,
        14,
        15,
        16,
        19
      ],
      [
        0,
        2,
        3,
        5,
        7,
        10,
        11,
        12,
        15
      ]
    ],
    "left": [
      [
        1,
        4,
        6,
        7,
        8,
        9,
        13,
        14,
        15,
        16,
        17,
        18,
        19
      ],
      [
        8,
        17,
        18
      ],
      [
        0,
        1,
        3,
        4,
        5,
        6,
        7,
        8,
        9,
        10,
        11,
        12,
        13,
        14,
        15,
        16,
        17,
        18,
        19
      ],
      [
        0,
        1,
        4,
        6,
        7,
        8,
        9,
        13,
        14,
        15,
        16,
        17,
        18,
        19
      ],
      [
        1,
        8,
        17,
        18
      ],
      [
        0,
        1,
        3,
        4,
        6,
        7,
        8,
        9,
        13,
        14,
        15,
        16,
        17,
        18,
        19
      ],
      [
        1,
        4,
        8,
        9,
        14,
        16,
        17,
        18
      ],
      [
        1,
        4,
        6,
        8,
        9,
        13,
        14,
        16,
        17,
        18,
        19
      ],
      [
        17,
        18
      ],
      [
        1,
        4,
        8,
        17,
        18
      ],
      [
        0,
        1,
        3,
        4,
        5,
        6,
        7,
        8,
        9,
        13,
        14,
        15,
        16,
        17,
        18,
        19
      ],
      [
        0,
        1,
        3,
        4,
        5,
        6,
        7,
        8,
        9,
        10,
        13,
        14,
        15,
        16,
        17,
        18,
        19
      ],
      [
        0,
        1,
        3,
        4,
        5,
        6,
        7,
        8,
        9,
        10,
        11,
        13,
        14,
        15,
        16,
        17,
        18,
        19
      ],
      [
        1,
        4,
        6,
        8,
        9,
        14,
        16,
        17,
        18
      ],
      [
        1,
        4,
        8,
        9,
        16,
        17,
        18
      ],
      [
        1,
        4,
        6,
        7,
        8,
        9,
        13,
        14,
        16,
        17,
        18,
        19
      ],
      [
        1,
        4,
        8,
        9,
        17,
        18
      ],
      [],
      [
        17
      ],
      [
        1,
        4,
        6,
        8,
        9,
        13,
        14,
        16,
        17,
        18
      ]
    ]
  }
}