{
  "relationships": {
    "behind": [
      [
        2
      ],
      [
        0,
        2,
        5
      ],
      [],
      [
        0,
        1,
        2,
        5
      ],
      [
        0,
        1,
        2,
        3,
        5
      ],
      [
        0,
        2
      ]
    ],
    "right": [
      [],
      [
        0,
        2,
        3,
        4,
        5
      ],
      [
        0,
        3,
        4
      ],
      [
        0,
        4
      ],
      [
        0
      ],
      [
        0,
        2,
        3,
        4
      ]
    ],
    "left": [
      [
        1,
        2,
        3,
        4,
        5
      ],
      [],
      [
        1,
        5
      ],
      [
        1,
        2,
        5
      ],
      [
        1,
        2,
        3,
        5
      ],
      [
        1
      ]
    ],
    "front": [
      [
        1,
        3,
        4,
        5
      ],
      [
        3,
        4
      ],
      [
        0,
        1,
        3,
        4,
        5
      ],
      [
        4
      ],
      [],
      [
        1,
        3,
        4
      ]
    ]
  },
  "image_index": 609,
  "split": "new",
  "directions": {
    "above": [
      0.0,
      0.0,
      1.0
    ],
    "left": [
      -0.6563112735748291,
      -0.7544902563095093,
      0.0
    ],
    "front": [
      0.754490315914154,
      -0.6563112735748291,
      -0.0
    ],
    "behind": [
      -0.754490315914154,
      0.6563112735748291,
      0.0
    ],
    "right": [
      0.6563112735748291,
      0.7544902563095093,
      -0.0
    ],
    "below": [
      -0.0,
      -0.0,
      -1.0
    ]
  },
  "objects": [
    {
      "color": "gray",
      "rotation": 189.27954273591928,
      "size": "large",
      "3d_coords": [
        -0.7753857970237732,
        2.768280267715454,
        0.30000001192092896
      ],
      "material": "rubber",
      "shape": "cube",
      "pixel_coords": [
        404,
        162,
        12.880599021911621
      ]
    },
    {
      "color": "cyan",
      "rotation": 342.36033693688,
      "size": "large",
      "3d_coords": [
        -0.5353594422340393,
        -2.210153102874756,
        0.30000001192092896
      ],
      "material": "rubber",
      "shape": "cylinder",
      "pixel_coords": [
        177,
        258,
        9.821410179138184
      ]
    },
    {
      "color": "green",
      "rotation": 77.43353693808976,
      "size": "large",
      "3d_coords": [
        -2.2317328453063965,
        1.6865653991699219,
        0.30000001192092896
      ],
      "material": "rubber",
      "shape": "cube",
      "pixel_coords": [
        308,
        155,
        13.203237533569336
      ]
    },
    {
      "color": "yellow",
      "rotation": 253.8436208881721,
      "size": "small",
      "3d_coords": [
        1.6610171794891357,
        -1.0787049531936646,
        0.30000001192092896
      ],
      "material": "rubber",
      "shape": "cylinder",
      "pixel_coords": [
        343,
        293,
        9.043399810791016
      ]
    },
    {
      "color": "green",
      "rotation": 24.13796466186332,
      "size": "large",
      "3d_coords": [
        2.8376238346099854,
        -1.622937560081482,
        0.30000001192092896
      ],
      "material": "rubber",
      "shape": "sphere",
      "pixel_coords": [
        379,
        352,
        7.9560394287109375
      ]
    },
    {
      "color": "blue",
      "rotation": 104.3967567136048,
      "size": "large",
      "3d_coords": [
        -0.8339999318122864,
        -1.2393027544021606,
        0.30000001192092896
      ],
      "material": "rubber",
      "shape": "cube",
      "pixel_coords": [
        222,
        229,
        10.582815170288086
      ]
    }
  ],
  "image_filename": "CLEVR_new_000609.png"
}