[
    {
        "shape_id": 59,
        "color": [
            0.029938214569925493,
            0.0,
            0.8
        ]
    },
    {
        "shape_id": 59,
        "color": [
            0.0,
            0.4949490295981203,
            0.8
        ]
    },
    {
        "shape_id": 59,
        "color": [
            0.06988442005768007,
            0.0,
            0.8
        ]
    },
    {
        "shape_id": 59,
        "color": [
            0.0,
            0.8,
            0.6373481714577118
        ]
    },
    {
        "shape_id": 59,
        "color": [
            0.0,
            0.8,
            0.7624774561418222
        ]
    },
    {
        "shape_id": 59,
        "color": [
            0.0,
            0.32294413862732585,
            0.8
        ]
    },
    {
        "shape_id": 59,
        "color": [
            0.0,
            0.6832904879135303,
            0.8
        ]
    },
    {
        "shape_id": 59,
        "color": [
            0.0,
            0.19866454214082374,
            0.8
        ]
    },
    {
        "shape_id": 59,
        "color": [
            0.0,
            0.8,
            0.5129403429195606
        ]
    },
    {
        "shape_id": 59,
        "color": [
            0.0,
            0.8,
            0.7933959789720781
        ]
    }
]